{
  "quarter": "2024-Q4",
  "generated_at": "2026-06-04T01:24:40Z",
  "total_value_usd": 254813765000,
  "num_holdings": 6,
  "holdings": [
    {
      "cusip": "573874104",
      "name_of_issuer": "MARVELL TECHNOLOGY INC",
      "title_of_class": "COM",
      "value_thousands": 86802213,
      "shares": 0,
      "share_type": "",
      "investment_discretion": "SOLE",
      "voting_sole": "785896",
      "voting_shared": "0",
      "voting_none": "0",
      "ticker": "MRVL",
      "display_name": "MARVELL TECHNOLOGY INC",
      "value_usd": 86802213000,
      "pct_of_portfolio": 34.06,
      "qoq_status": "new",
      "qoq_shares_delta": 0,
      "qoq_value_delta": 86802213
    },
    {
      "cusip": "92840M102",
      "name_of_issuer": "VISTRA CORP",
      "title_of_class": "COM",
      "value_thousands": 59063094,
      "shares": 0,
      "share_type": "",
      "investment_discretion": "SOLE",
      "voting_sole": "428397",
      "voting_shared": "0",
      "voting_none": "0",
      "ticker": "VST",
      "display_name": "VISTRA CORP",
      "value_usd": 59063094000,
      "pct_of_portfolio": 23.18,
      "qoq_status": "new",
      "qoq_shares_delta": 0,
      "qoq_value_delta": 59063094
    },
    {
      "cusip": "92537N108",
      "name_of_issuer": "VERTIV HOLDINGS CO",
      "title_of_class": "COM CL A",
      "value_thousands": 51709137,
      "shares": 0,
      "share_type": "",
      "investment_discretion": "SOLE",
      "voting_sole": "455146",
      "voting_shared": "0",
      "voting_none": "0",
      "ticker": "VRT",
      "display_name": "VERTIV HOLDINGS CO-A",
      "value_usd": 51709137000,
      "pct_of_portfolio": 20.29,
      "qoq_status": "new",
      "qoq_shares_delta": 0,
      "qoq_value_delta": 51709137
    },
    {
      "cusip": "87422Q109",
      "name_of_issuer": "TALEN ENERGY CORP",
      "title_of_class": "COM",
      "value_thousands": 27979751,
      "shares": 0,
      "share_type": "",
      "investment_discretion": "SOLE",
      "voting_sole": "138878",
      "voting_shared": "0",
      "voting_none": "0",
      "ticker": "TLN",
      "display_name": "TALEN ENERGY CORP",
      "value_usd": 27979751000,
      "pct_of_portfolio": 10.98,
      "qoq_status": "new",
      "qoq_shares_delta": 0,
      "qoq_value_delta": 27979751
    },
    {
      "cusip": "21037T109",
      "name_of_issuer": "CONSTELLATION ENERGY CORP",
      "title_of_class": "COM",
      "value_thousands": 21565644,
      "shares": 0,
      "share_type": "",
      "investment_discretion": "SOLE",
      "voting_sole": "96400",
      "voting_shared": "0",
      "voting_none": "0",
      "ticker": "CEG",
      "display_name": "CONSTELLATION ENERGY",
      "value_usd": 21565644000,
      "pct_of_portfolio": 8.46,
      "qoq_status": "new",
      "qoq_shares_delta": 0,
      "qoq_value_delta": 21565644
    },
    {
      "cusip": "607828100",
      "name_of_issuer": "MODINE MFG CO",
      "title_of_class": "COM",
      "value_thousands": 7693926,
      "shares": 0,
      "share_type": "",
      "investment_discretion": "SOLE",
      "voting_sole": "66367",
      "voting_shared": "0",
      "voting_none": "0",
      "ticker": "MOD",
      "display_name": "MODINE MANUFACTURING CO",
      "value_usd": 7693926000,
      "pct_of_portfolio": 3.02,
      "qoq_status": "new",
      "qoq_shares_delta": 0,
      "qoq_value_delta": 7693926
    }
  ]
}